Vending_Machine_verilog_Project/vending_machine.v
module vending_machine (
    input clk,
    input reset,
    input [3:0] money_in,
    input [2:0] product_code,   // 3 bits (0-7)
    output reg dispense,
    output reg [3:0] change,
    output reg out_of_stock
);

    reg [3:0] product_price;

    // Stock count for each product (6 products)
    reg [3:0] stock [0:5];

    // Combinational block to determine product price
    always @(*) begin
        case (product_code)
            3'b000: product_price = 4'd15;
            3'b001: product_price = 4'd5;
            3'b010: product_price = 4'd10;
            3'b011: product_price = 4'd5;
            3'b100: product_price = 4'd5;
            3'b101: product_price = 4'd10;
            default: product_price = 4'd15;
        endcase
    end

    // Sequential block for vending machine logic
    always @(posedge clk or posedge reset) begin
        if (reset) begin
            stock[0] <= 4'd10;
            stock[1] <= 4'd0;
            stock[2] <= 4'd3;
            stock[3] <= 4'd1;
            stock[4] <= 4'd5;
            stock[5] <= 4'd8;

            dispense <= 0;
            change <= 0;
            out_of_stock <= 0;
        end else begin
            if (product_code <= 5) begin
                if (stock[product_code] == 0) begin
                    dispense <= 0;
                    change <= money_in;
                    out_of_stock <= 1;
                end else if (money_in >= product_price) begin
                    dispense <= 1;
                    change <= money_in - product_price;
                    out_of_stock <= 0;
                    stock[product_code] <= stock[product_code] - 1;
                end else begin
                    dispense <= 0;
                    change <= money_in;
                    out_of_stock <= 0;
                end
            end else begin
                dispense <= 0;
                change <= money_in;
                out_of_stock <= 1;
            end
        end
    end

    initial begin
        $dumpfile("dump.vcd");
        $dumpvars(0, vending_machine);
    end

endmodule

Vending_Machine_verilog_Project/dump.vcd
$date
	Wed Aug 13 16:03:15 2025
$end
$version
	Icarus Verilog
$end
$timescale
	1ps
$end
$scope module vending_machine $end
$var wire 1 ! clk $end
$var wire 4 " money_in [3:0] $end
$var wire 3 # product_code [2:0] $end
$var wire 1 $ reset $end
$var reg 4 % change [3:0] $end
$var reg 1 & dispense $end
$var reg 1 ' out_of_stock $end
$var reg 4 ( product_price [3:0] $end
$upscope $end
$enddefinitions $end
#0
$dumpvars
b1111 (
0'
0&
b0 %
1$
b0 #
b0 "
1!
$end
#5000
0!
#10000
1&
1!
b1111 "
0$
#15000
b101 (
b1 #
b1010 "
0!
#20000
1'
b1010 %
0&
1!
#25000
b1010 (
b10 #
b1000 "
0!
#30000
0'
b1000 %
1!
#35000
b101 (
b11 #
b101 "
0!
#40000
b0 %
1&
1!
#45000
b1111 (
b111 #
b1111 "
0!
#50000
1'
b1111 %
0&
1!
#55000
b101 (
b11 #
b101 "
0!
#60000
b101 %
1!
